flask_prom/__init__.py
flask_prom-0.1.0.dist-info/LICENSE
flask_prom-0.1.0.dist-info/METADATA
flask_prom-0.1.0.dist-info/WHEEL
flask_prom-0.1.0.dist-info/top_level.txt
flask_prom-0.1.0.dist-info/RECORD
